README.rst
setup.py
zbx2slack.py
zbx2slack.egg-info/PKG-INFO
zbx2slack.egg-info/SOURCES.txt
zbx2slack.egg-info/dependency_links.txt
zbx2slack.egg-info/entry_points.txt
zbx2slack.egg-info/requires.txt
zbx2slack.egg-info/top_level.txt