Metadata-Version: 1.1
Name: zbx2slack
Version: 0.1.1
Summary: command-line tool for Zabbix Alert Notification to Slack.
Home-page: https://github.com/laughk/zbx2slack
Author: Kei Iwasaki
Author-email: me@laughk.org
License: MIT License
Platform: UNKNOWN
Classifier: License :: OSI Approved :: MIT License
Classifier: Programming Language :: Python :: 2.6
Classifier: Programming Language :: Python :: 2.7
Classifier: Programming Language :: Python :: 3
Classifier: Programming Language :: Python :: 3.3
Classifier: Programming Language :: Python :: 3.4
Classifier: Programming Language :: Python :: 3.5
